eCHORDlib/BM3D_GUI_pg_v1.py
eCHORDlib/BM3D_v1.ui
eCHORDlib/Fct_profil_modification.py
eCHORDlib/general_functions.py
eCHORDlib/indexation_tiff_sur_GPU_v19_lib.py
eCHORDlib/indexation_tiff_sur_GPU_v20_lib.py
eCHORDlib/IPF_V1.py
eCHORDlib/NLMD_GUI_pg_v1.py
eCHORDlib/NLMD_v1.ui
eCHORDlib/remOutliers_v3.ui
eCHORDlib/remOutliersGUI_pg_v2.py
eCHORDlib/requirements.txt
eCHORDlib/Rotations.py
eCHORDlib/stackViewer_v2.ui
eCHORDlib/stackViewerGUI_pg_v2.py
eCHORDlib/Symetry.py
eCHORDlib/test_general_functions.py
eCHORDlib/VSNR_GUI_pg_v1.py
eCHORDlib/VSNR_v1.ui
eCHORDlib/Xallo.py
echordlib-1.0.2.dist-info/LICENSE
echordlib-1.0.2.dist-info/METADATA
echordlib-1.0.2.dist-info/WHEEL
echordlib-1.0.2.dist-info/RECORD
