Metadata-Version: 2.1
Name: echordlib
Version: 1.0.2
Summary: mandatory library for CHORD framework (image tratment, indexing and visualization)
License: CeCILL
Author: Langlois Cyril, Gabriel L'Hôte, Clément Lafond, Joël Lachambre
Requires-Python: >=3.10,<4.0
Classifier: License :: Other/Proprietary License
Classifier: Programming Language :: Python :: 3
Classifier: Programming Language :: Python :: 3.10
Classifier: Programming Language :: Python :: 3.11
Classifier: Programming Language :: Python :: 3.12
Requires-Dist: PyQt5 (==5.15.10)
Requires-Dist: PyQt5-Qt5 (==5.15.2)
Requires-Dist: bm3d (>=4.0.1,<5.0.0)
Requires-Dist: cuda-python (==12.2.0)
Requires-Dist: cupy-cuda12x (>=13.0.0,<14.0.0)
Requires-Dist: cv (>=1.0.0,<2.0.0)
Requires-Dist: dill (>=0.3.8,<0.4.0)
Requires-Dist: h5py (>=3.10.0,<4.0.0)
Requires-Dist: ipywidgets (>=8.1.1,<9.0.0)
Requires-Dist: joblib (>=1.3.2,<2.0.0)
Requires-Dist: largestinteriorrectangle (>=0.2.0,<0.3.0)
Requires-Dist: matplotlib (>=3.8.2,<4.0.0)
Requires-Dist: opencv-python (>=4.8.1.78,<5.0.0.0)
Requires-Dist: orix (>=0.11.1,<0.12.0)
Requires-Dist: pyqtgraph (>=0.13.3,<0.14.0)
Requires-Dist: pyquaternion (>=0.9.9,<0.10.0)
Requires-Dist: scikit-image (>=0.22.0,<0.23.0)
Requires-Dist: scikit-learn (>=1.4.0,<2.0.0)
Requires-Dist: tifffile (>=2023.12.9,<2024.0.0)
Requires-Dist: tqdm (>=4.66.1,<5.0.0)
